django_staticfiles_noimport-0.9.data/scripts/collectstatic
django_staticfiles_noimport-0.9.data/scripts/findstatic
staticfiles_noimport/__init__.py
staticfiles_noimport/finders.py
django_staticfiles_noimport-0.9.dist-info/LICENSE
django_staticfiles_noimport-0.9.dist-info/METADATA
django_staticfiles_noimport-0.9.dist-info/WHEEL
django_staticfiles_noimport-0.9.dist-info/top_level.txt
django_staticfiles_noimport-0.9.dist-info/RECORD
