Metadata-Version: 2.1
Name: django-staticfiles-noimport
Version: 0.9
Summary: Allows Django staticfiles commands to be run without importing all apps.
Home-page: https://github.com/roverdotcom/django-staticfiles-noimport
Author: Philip Kimmey
Author-email: philip+pypi@rover.com
License: UNKNOWN
Platform: UNKNOWN
Classifier: License :: OSI Approved :: MIT License
Classifier: Programming Language :: Python :: 3 :: Only
Classifier: Framework :: Django
Requires-Python: >=3.6
Requires-Dist: Django (>=1.11)
